woodchips/__init__.py
woodchips/_version.py
woodchips/logger.py
woodchips/py.typed
woodchips-2.0.0.dist-info/licenses/LICENSE
woodchips-2.0.0.dist-info/METADATA
woodchips-2.0.0.dist-info/WHEEL
woodchips-2.0.0.dist-info/top_level.txt
woodchips-2.0.0.dist-info/RECORD
